pschecker/__init__.py
pschecker/cli.py
pschecker/helpers.py
pschecker/pschecker.py
pschecker/checks/__init__.py
pschecker/checks/domain_names.py
pschecker/checks/fail.py
pschecker/checks/firewall.py
pschecker/checks/host_listening.py
pschecker/checks/last_update.py
pschecker/checks/root_password.py
pschecker/checks/success.py
pschecker/checks/warning.py
pschecker-0.2.4.dist-info/DESCRIPTION.rst
pschecker-0.2.4.dist-info/LICENSE.txt
pschecker-0.2.4.dist-info/METADATA
pschecker-0.2.4.dist-info/RECORD
pschecker-0.2.4.dist-info/WHEEL
pschecker-0.2.4.dist-info/entry_points.txt
pschecker-0.2.4.dist-info/metadata.json
pschecker-0.2.4.dist-info/top_level.txt
